{
  "project_info": {
    "project_number": "892826535808",
    "project_id": "jugend-eb0c3",
    "storage_bucket": "jugend-eb0c3.appspot.com"
  },
  "client": [
    {
      "client_info": {
        "mobilesdk_app_id": "1:892826535808:android:e8c2f327c67f465db5e365",
        "android_client_info": {
          "package_name": "app.alphaev"
        }
      },
      "oauth_client": [
        {
          "client_id": "892826535808-ghkspnm25j4bm7bfutd1lo8vv15f8fc5.apps.googleusercontent.com",
          "client_type": 3
        }
      ],
      "api_key": [
        {
          "current_key": "AIzaSyCyXT70FAoONaQYqti2pfS3ttuW-9pUhFM"
        }
      ],
      "services": {
        "appinvite_service": {
          "other_platform_oauth_client": [
            {
              "client_id": "892826535808-ghkspnm25j4bm7bfutd1lo8vv15f8fc5.apps.googleusercontent.com",
              "client_type": 3
            }
          ]
        }
      }
    }
  ],
  "configuration_version": "1"
}